fastapi_pypendency/__init__.py
fastapi_pypendency-0.1.3.dist-info/licenses/LICENSE
fastapi_pypendency-0.1.3.dist-info/METADATA
fastapi_pypendency-0.1.3.dist-info/WHEEL
fastapi_pypendency-0.1.3.dist-info/top_level.txt
fastapi_pypendency-0.1.3.dist-info/RECORD
